openscienceplot_matplotlib/__init__.py
openscienceplot_matplotlib/_version.py
openscienceplot_matplotlib-0.2.2.dist-info/LICENSE
openscienceplot_matplotlib-0.2.2.dist-info/METADATA
openscienceplot_matplotlib-0.2.2.dist-info/WHEEL
openscienceplot_matplotlib-0.2.2.dist-info/top_level.txt
openscienceplot_matplotlib-0.2.2.dist-info/RECORD
